pimpygui/__init__.py
pimpygui/color_widget.py
pimpygui/edge_effect_dialog.py
pimpygui/effect_dialog.py
pimpygui/gallery.py
pimpygui/history_stack.py
pimpygui/image_widget.py
pimpygui/main_colors_effect_dialog.py
pimpygui/paint_by_number_effect_dialog.py
pimpygui/smooth_effect_dialog.py
pimpygui/utils.py
pimpygui/ui/edge_effect_widget.ui
pimpygui/ui/gallery.ui
pimpygui/ui/main_colors_effect_widget.ui
pimpygui/ui/paint_by_number_effect_widget.ui
pimpygui/ui/smooth_effect_widget.ui
pimpygui-0.1.1.dist-info/LICENSE.txt
pimpygui-0.1.1.dist-info/METADATA
pimpygui-0.1.1.dist-info/WHEEL
pimpygui-0.1.1.dist-info/entry_points.txt
pimpygui-0.1.1.dist-info/top_level.txt
pimpygui-0.1.1.dist-info/RECORD
