Metadata-Version: 2.1
Name: pimpygui
Version: 0.1.1
Summary: Graphical user interface for pimpy
Home-page: https://gitlab.com/pschill/pimpy
Author: Philip Schill
Author-email: philip.schill@gmx.de
License: UNKNOWN
Platform: UNKNOWN
Classifier: Programming Language :: Python :: 3.6
Classifier: Programming Language :: Python :: 3.7
Classifier: License :: OSI Approved :: GNU General Public License v3 (GPLv3)
Classifier: Operating System :: OS Independent
Classifier: Topic :: Artistic Software
Requires-Python: >=3.6
Requires-Dist: pimpy (>=0.1.0)
Requires-Dist: PySide2 (>=5.12)
